mypackage/__init__.py
mypackage/data_utils.py
mypackage/math_utils.py
mypackage/module1.py
mypackage/module2.py
mypackage/relative_import_demo.py
mypackage/string_utils.py
mypackage/subpackage/__init__.py
mypackage/subpackage/advanced_math.py
mypackage/subpackage/module3.py
mypackagemypackagemeta-1.0.1.dist-info/LICENSE.txt
mypackagemypackagemeta-1.0.1.dist-info/METADATA
mypackagemypackagemeta-1.0.1.dist-info/WHEEL
mypackagemypackagemeta-1.0.1.dist-info/top_level.txt
mypackagemypackagemeta-1.0.1.dist-info/RECORD
