Metadata-Version: 2.1
Name: mypackagemypackagemeta
Version: 1.0.1
Summary: A sample Python package
Author: Python learner
Author-email: Python learner <hestudio@hestudio.org>
Requires-Python: >=3.7
License-File: LICENSE.txt
Requires-Dist: requests >=2.25.0
Requires-Dist: click
